sepmachine/__init__.py
sepmachine/capture/__init__.py
sepmachine/capture/adb.py
sepmachine/capture/base.py
sepmachine/capture/empty.py
sepmachine/capture/scrcpy.py
sepmachine/handler/__init__.py
sepmachine/handler/base.py
sepmachine/handler/keras.py
sepmachine/handler/normal.py
sepmachine/pipeline/__init__.py
sepmachine/pipeline/base.py
sepmachine_macos-0.3.5.dist-info/LICENSE
sepmachine_macos-0.3.5.dist-info/METADATA
sepmachine_macos-0.3.5.dist-info/WHEEL
sepmachine_macos-0.3.5.dist-info/top_level.txt
sepmachine_macos-0.3.5.dist-info/RECORD
