Metadata-Version: 2.1
Name: sepmachine-macos
Version: 0.3.5
Summary: stagesepx + video capture = auto workflow
Home-page: https://github.com/kylin4ever/sepmachine
Author: kylin4ever
Author-email: bestisor@163.com
License: MIT
Platform: UNKNOWN
Classifier: License :: OSI Approved :: MIT License
Classifier: Programming Language :: Python
Classifier: Programming Language :: Python :: 3
Classifier: Programming Language :: Python :: 3.6
Classifier: Programming Language :: Python :: 3.7
Requires-Python: >=3.6,<=3.10.0
License-File: LICENSE
Requires-Dist: stagesepx (>=0.10.4)
Requires-Dist: loguru (>=0.2.5)
Requires-Dist: minadb (>=0.3.1)
Requires-Dist: ffmpeg-python (>=0.2.0)
Requires-Dist: tensorflow-macos (>=2.9.0)
